[
  {
    "@id": "http://hl7.org/fhir/ElementDefinition_Constraint/base",
    "@type": [
      "https://lschema.org/Schema"
    ],
    "https://lschema.org/layer": [
      {
        "@id": "http://hl7.org/fhir/ElementDefinition_Constraint",
        "@type": [
          "http://hl7.org/fhir/ElementDefinition_Constraint"
        ],
        "https://lschema.org/Object#attributes": [
          {
            "@id": "http://hl7.org/fhir/ElementDefinition_Constraint#human",
            "@type": [
              "https://lschema.org/Value"
            ],
            "https://lschema.org/attributeName": [
              {
                "@value": "human"
              }
            ],
            "https://lschema.org/description": [
              {
                "@value": "A sequence of Unicode characters"
              }
            ],
            "https://lschema.org/targetType": [
              {
                "@id": "string"
              }
            ],
            "https://lschema.org/validation#pattern": [
              {
                "@value": "^[ \\r\\n\\t\\S]+$"
              }
            ]
          },
          {
            "@id": "http://hl7.org/fhir/ElementDefinition_Constraint#_requirements",
            "@type": [
              "https://lschema.org/Reference"
            ],
            "https://lschema.org/Reference#reference": [
              {
                "@id": "http://hl7.org/fhir/Element"
              }
            ],
            "https://lschema.org/attributeName": [
              {
                "@value": "_requirements"
              }
            ]
          },
          {
            "@id": "http://hl7.org/fhir/ElementDefinition_Constraint#_key",
            "@type": [
              "https://lschema.org/Reference"
            ],
            "https://lschema.org/Reference#reference": [
              {
                "@id": "http://hl7.org/fhir/Element"
              }
            ],
            "https://lschema.org/attributeName": [
              {
                "@value": "_key"
              }
            ]
          },
          {
            "@id": "http://hl7.org/fhir/ElementDefinition_Constraint#_severity",
            "@type": [
              "https://lschema.org/Reference"
            ],
            "https://lschema.org/Reference#reference": [
              {
                "@id": "http://hl7.org/fhir/Element"
              }
            ],
            "https://lschema.org/attributeName": [
              {
                "@value": "_severity"
              }
            ]
          },
          {
            "@id": "http://hl7.org/fhir/ElementDefinition_Constraint#xpath",
            "@type": [
              "https://lschema.org/Value"
            ],
            "https://lschema.org/attributeName": [
              {
                "@value": "xpath"
              }
            ],
            "https://lschema.org/description": [
              {
                "@value": "A sequence of Unicode characters"
              }
            ],
            "https://lschema.org/targetType": [
              {
                "@id": "string"
              }
            ],
            "https://lschema.org/validation#pattern": [
              {
                "@value": "^[ \\r\\n\\t\\S]+$"
              }
            ]
          },
          {
            "@id": "http://hl7.org/fhir/ElementDefinition_Constraint#key",
            "@type": [
              "https://lschema.org/Reference"
            ],
            "https://lschema.org/Reference#reference": [
              {
                "@id": "http://hl7.org/fhir/id"
              }
            ],
            "https://lschema.org/attributeName": [
              {
                "@value": "key"
              }
            ]
          },
          {
            "@id": "http://hl7.org/fhir/ElementDefinition_Constraint#id",
            "@type": [
              "https://lschema.org/Value"
            ],
            "https://lschema.org/attributeName": [
              {
                "@value": "id"
              }
            ],
            "https://lschema.org/description": [
              {
                "@value": "A sequence of Unicode characters"
              }
            ],
            "https://lschema.org/targetType": [
              {
                "@id": "string"
              }
            ],
            "https://lschema.org/validation#pattern": [
              {
                "@value": "^[ \\r\\n\\t\\S]+$"
              }
            ]
          },
          {
            "@id": "http://hl7.org/fhir/ElementDefinition_Constraint#extension",
            "@type": [
              "https://lschema.org/Array"
            ],
            "https://lschema.org/Array#items": [
              {
                "@id": "http://hl7.org/fhir/ElementDefinition_Constraint#extension.*",
                "@type": [
                  "https://lschema.org/Reference"
                ],
                "https://lschema.org/Reference#reference": [
                  {
                    "@id": "http://hl7.org/fhir/Extension"
                  }
                ]
              }
            ],
            "https://lschema.org/attributeName": [
              {
                "@value": "extension"
              }
            ]
          },
          {
            "@id": "http://hl7.org/fhir/ElementDefinition_Constraint#_human",
            "@type": [
              "https://lschema.org/Reference"
            ],
            "https://lschema.org/Reference#reference": [
              {
                "@id": "http://hl7.org/fhir/Element"
              }
            ],
            "https://lschema.org/attributeName": [
              {
                "@value": "_human"
              }
            ]
          },
          {
            "@id": "http://hl7.org/fhir/ElementDefinition_Constraint#modifierExtension",
            "@type": [
              "https://lschema.org/Array"
            ],
            "https://lschema.org/Array#items": [
              {
                "@id": "http://hl7.org/fhir/ElementDefinition_Constraint#modifierExtension.*",
                "@type": [
                  "https://lschema.org/Reference"
                ],
                "https://lschema.org/Reference#reference": [
                  {
                    "@id": "http://hl7.org/fhir/Extension"
                  }
                ]
              }
            ],
            "https://lschema.org/attributeName": [
              {
                "@value": "modifierExtension"
              }
            ]
          },
          {
            "@id": "http://hl7.org/fhir/ElementDefinition_Constraint#_xpath",
            "@type": [
              "https://lschema.org/Reference"
            ],
            "https://lschema.org/Reference#reference": [
              {
                "@id": "http://hl7.org/fhir/Element"
              }
            ],
            "https://lschema.org/attributeName": [
              {
                "@value": "_xpath"
              }
            ]
          },
          {
            "@id": "http://hl7.org/fhir/ElementDefinition_Constraint#source",
            "@type": [
              "https://lschema.org/Value"
            ],
            "https://lschema.org/attributeName": [
              {
                "@value": "source"
              }
            ],
            "https://lschema.org/description": [
              {
                "@value": "A URI that is a reference to a canonical URL on a FHIR resource"
              }
            ],
            "https://lschema.org/targetType": [
              {
                "@id": "string"
              }
            ],
            "https://lschema.org/validation#pattern": [
              {
                "@value": "^\\S*$"
              }
            ]
          },
          {
            "@id": "http://hl7.org/fhir/ElementDefinition_Constraint#_expression",
            "@type": [
              "https://lschema.org/Reference"
            ],
            "https://lschema.org/Reference#reference": [
              {
                "@id": "http://hl7.org/fhir/Element"
              }
            ],
            "https://lschema.org/attributeName": [
              {
                "@value": "_expression"
              }
            ]
          },
          {
            "@id": "http://hl7.org/fhir/ElementDefinition_Constraint#requirements",
            "@type": [
              "https://lschema.org/Value"
            ],
            "https://lschema.org/attributeName": [
              {
                "@value": "requirements"
              }
            ],
            "https://lschema.org/description": [
              {
                "@value": "A sequence of Unicode characters"
              }
            ],
            "https://lschema.org/targetType": [
              {
                "@id": "string"
              }
            ],
            "https://lschema.org/validation#pattern": [
              {
                "@value": "^[ \\r\\n\\t\\S]+$"
              }
            ]
          },
          {
            "@id": "http://hl7.org/fhir/ElementDefinition_Constraint#severity",
            "@type": [
              "https://lschema.org/Value"
            ],
            "https://lschema.org/attributeName": [
              {
                "@value": "severity"
              }
            ],
            "https://lschema.org/description": [
              {
                "@value": "Identifies the impact constraint violation has on the conformance of the instance."
              }
            ],
            "https://lschema.org/validation#enumeration": [
              {
                "@value": "error"
              },
              {
                "@value": "warning"
              }
            ]
          },
          {
            "@id": "http://hl7.org/fhir/ElementDefinition_Constraint#expression",
            "@type": [
              "https://lschema.org/Value"
            ],
            "https://lschema.org/attributeName": [
              {
                "@value": "expression"
              }
            ],
            "https://lschema.org/description": [
              {
                "@value": "A sequence of Unicode characters"
              }
            ],
            "https://lschema.org/targetType": [
              {
                "@id": "string"
              }
            ],
            "https://lschema.org/validation#pattern": [
              {
                "@value": "^[ \\r\\n\\t\\S]+$"
              }
            ]
          }
        ]
      }
    ],
    "https://lschema.org/targetType": [
      {
        "@id": "http://hl7.org/fhir/ElementDefinition_Constraint"
      }
    ]
  }
]