[
  {
    "@id": "http://hl7.org/fhir/EvidenceVariable_Characteristic/description",
    "@type": [
      "https://lschema.org/Overlay"
    ],
    "https://lschema.org/layer": [
      {
        "@id": "http://hl7.org/fhir/EvidenceVariable_Characteristic",
        "@type": [
          "https://lschema.org/Object",
          "http://hl7.org/fhir/EvidenceVariable_Characteristic"
        ],
        "https://lschema.org/Object/attributes": [
          {
            "@id": "http://hl7.org/fhir/EvidenceVariable_Characteristic#id",
            "@type": [
              "https://lschema.org/Value"
            ],
            "https://lschema.org/description": [
              {
                "@value": "A sequence of Unicode characters"
              }
            ]
          },
          {
            "@id": "http://hl7.org/fhir/EvidenceVariable_Characteristic#definitionCanonical",
            "@type": [
              "https://lschema.org/Value"
            ],
            "https://lschema.org/description": [
              {
                "@value": "Define members of the evidence element using Codes (such as condition, medication, or observation), Expressions ( using an expression language such as FHIRPath or CQL) or DataRequirements (such as Diabetes diagnosis onset in the last year)."
              }
            ]
          },
          {
            "@id": "http://hl7.org/fhir/EvidenceVariable_Characteristic#participantEffectiveDateTime",
            "@type": [
              "https://lschema.org/Value"
            ],
            "https://lschema.org/description": [
              {
                "@value": "Indicates what effective period the study covers."
              }
            ]
          },
          {
            "@id": "http://hl7.org/fhir/EvidenceVariable_Characteristic#groupMeasure",
            "@type": [
              "https://lschema.org/Value"
            ],
            "https://lschema.org/description": [
              {
                "@value": "Indicates how elements are aggregated within the study effective period."
              }
            ]
          },
          {
            "@id": "http://hl7.org/fhir/EvidenceVariable_Characteristic#exclude",
            "@type": [
              "https://lschema.org/Value"
            ],
            "https://lschema.org/description": [
              {
                "@value": "Value of \"true\" or \"false\""
              }
            ]
          },
          {
            "@id": "http://hl7.org/fhir/EvidenceVariable_Characteristic#description",
            "@type": [
              "https://lschema.org/Value"
            ],
            "https://lschema.org/description": [
              {
                "@value": "A sequence of Unicode characters"
              }
            ]
          }
        ]
      }
    ],
    "https://lschema.org/targetType": [
      {
        "@id": "http://hl7.org/fhir/EvidenceVariable_Characteristic"
      }
    ]
  }
]