[
  {
    "@id": "http://hl7.org/fhir/ExampleScenario_Actor/base",
    "@type": [
      "https://lschema.org/Schema"
    ],
    "https://lschema.org/layer": [
      {
        "@id": "http://hl7.org/fhir/ExampleScenario_Actor",
        "@type": [
          "http://hl7.org/fhir/ExampleScenario_Actor"
        ],
        "https://lschema.org/Object#attributes": [
          {
            "@id": "http://hl7.org/fhir/ExampleScenario_Actor#name",
            "@type": [
              "https://lschema.org/Value"
            ],
            "https://lschema.org/attributeName": [
              {
                "@value": "name"
              }
            ],
            "https://lschema.org/description": [
              {
                "@value": "A sequence of Unicode characters"
              }
            ],
            "https://lschema.org/targetType": [
              {
                "@id": "string"
              }
            ],
            "https://lschema.org/validation#pattern": [
              {
                "@value": "^[ \\r\\n\\t\\S]+$"
              }
            ]
          },
          {
            "@id": "http://hl7.org/fhir/ExampleScenario_Actor#description",
            "@type": [
              "https://lschema.org/Value"
            ],
            "https://lschema.org/attributeName": [
              {
                "@value": "description"
              }
            ],
            "https://lschema.org/description": [
              {
                "@value": "A string that may contain Github Flavored Markdown syntax for optional processing by a mark down presentation engine"
              }
            ],
            "https://lschema.org/targetType": [
              {
                "@id": "string"
              }
            ],
            "https://lschema.org/validation#pattern": [
              {
                "@value": "^[ \\r\\n\\t\\S]+$"
              }
            ]
          },
          {
            "@id": "http://hl7.org/fhir/ExampleScenario_Actor#id",
            "@type": [
              "https://lschema.org/Value"
            ],
            "https://lschema.org/attributeName": [
              {
                "@value": "id"
              }
            ],
            "https://lschema.org/description": [
              {
                "@value": "A sequence of Unicode characters"
              }
            ],
            "https://lschema.org/targetType": [
              {
                "@id": "string"
              }
            ],
            "https://lschema.org/validation#pattern": [
              {
                "@value": "^[ \\r\\n\\t\\S]+$"
              }
            ]
          },
          {
            "@id": "http://hl7.org/fhir/ExampleScenario_Actor#_name",
            "@type": [
              "https://lschema.org/Reference"
            ],
            "https://lschema.org/Reference#reference": [
              {
                "@id": "http://hl7.org/fhir/Element"
              }
            ],
            "https://lschema.org/attributeName": [
              {
                "@value": "_name"
              }
            ]
          },
          {
            "@id": "http://hl7.org/fhir/ExampleScenario_Actor#extension",
            "@type": [
              "https://lschema.org/Array"
            ],
            "https://lschema.org/Array#items": [
              {
                "@id": "http://hl7.org/fhir/ExampleScenario_Actor#extension.*",
                "@type": [
                  "https://lschema.org/Reference"
                ],
                "https://lschema.org/Reference#reference": [
                  {
                    "@id": "http://hl7.org/fhir/Extension"
                  }
                ]
              }
            ],
            "https://lschema.org/attributeName": [
              {
                "@value": "extension"
              }
            ]
          },
          {
            "@id": "http://hl7.org/fhir/ExampleScenario_Actor#type",
            "@type": [
              "https://lschema.org/Value"
            ],
            "https://lschema.org/attributeName": [
              {
                "@value": "type"
              }
            ],
            "https://lschema.org/description": [
              {
                "@value": "The type of actor - person or system."
              }
            ],
            "https://lschema.org/validation#enumeration": [
              {
                "@value": "person"
              },
              {
                "@value": "entity"
              }
            ]
          },
          {
            "@id": "http://hl7.org/fhir/ExampleScenario_Actor#_description",
            "@type": [
              "https://lschema.org/Reference"
            ],
            "https://lschema.org/Reference#reference": [
              {
                "@id": "http://hl7.org/fhir/Element"
              }
            ],
            "https://lschema.org/attributeName": [
              {
                "@value": "_description"
              }
            ]
          },
          {
            "@id": "http://hl7.org/fhir/ExampleScenario_Actor#_type",
            "@type": [
              "https://lschema.org/Reference"
            ],
            "https://lschema.org/Reference#reference": [
              {
                "@id": "http://hl7.org/fhir/Element"
              }
            ],
            "https://lschema.org/attributeName": [
              {
                "@value": "_type"
              }
            ]
          },
          {
            "@id": "http://hl7.org/fhir/ExampleScenario_Actor#modifierExtension",
            "@type": [
              "https://lschema.org/Array"
            ],
            "https://lschema.org/Array#items": [
              {
                "@id": "http://hl7.org/fhir/ExampleScenario_Actor#modifierExtension.*",
                "@type": [
                  "https://lschema.org/Reference"
                ],
                "https://lschema.org/Reference#reference": [
                  {
                    "@id": "http://hl7.org/fhir/Extension"
                  }
                ]
              }
            ],
            "https://lschema.org/attributeName": [
              {
                "@value": "modifierExtension"
              }
            ]
          },
          {
            "@id": "http://hl7.org/fhir/ExampleScenario_Actor#actorId",
            "@type": [
              "https://lschema.org/Value"
            ],
            "https://lschema.org/attributeName": [
              {
                "@value": "actorId"
              }
            ],
            "https://lschema.org/description": [
              {
                "@value": "A sequence of Unicode characters"
              }
            ],
            "https://lschema.org/targetType": [
              {
                "@id": "string"
              }
            ],
            "https://lschema.org/validation#pattern": [
              {
                "@value": "^[ \\r\\n\\t\\S]+$"
              }
            ]
          },
          {
            "@id": "http://hl7.org/fhir/ExampleScenario_Actor#_actorId",
            "@type": [
              "https://lschema.org/Reference"
            ],
            "https://lschema.org/Reference#reference": [
              {
                "@id": "http://hl7.org/fhir/Element"
              }
            ],
            "https://lschema.org/attributeName": [
              {
                "@value": "_actorId"
              }
            ]
          }
        ]
      }
    ],
    "https://lschema.org/targetType": [
      {
        "@id": "http://hl7.org/fhir/ExampleScenario_Actor"
      }
    ]
  }
]