[
  {
    "@id": "http://hl7.org/fhir/ExplanationOfBenefit_Total/base",
    "@type": [
      "https://lschema.org/Schema"
    ],
    "https://lschema.org/layer": [
      {
        "@id": "http://hl7.org/fhir/ExplanationOfBenefit_Total",
        "https://lschema.org/Object#attributes": [
          {
            "@id": "http://hl7.org/fhir/ExplanationOfBenefit_Total#category",
            "@type": [
              "https://lschema.org/Reference"
            ],
            "https://lschema.org/Reference#reference": [
              {
                "@id": "http://hl7.org/fhir/CodeableConcept"
              }
            ],
            "https://lschema.org/attributeName": [
              {
                "@value": "category"
              }
            ]
          },
          {
            "@id": "http://hl7.org/fhir/ExplanationOfBenefit_Total#amount",
            "@type": [
              "https://lschema.org/Reference"
            ],
            "https://lschema.org/Reference#reference": [
              {
                "@id": "http://hl7.org/fhir/Money"
              }
            ],
            "https://lschema.org/attributeName": [
              {
                "@value": "amount"
              }
            ]
          },
          {
            "@id": "http://hl7.org/fhir/ExplanationOfBenefit_Total#id",
            "@type": [
              "https://lschema.org/Value"
            ],
            "https://lschema.org/attributeName": [
              {
                "@value": "id"
              }
            ],
            "https://lschema.org/description": [
              {
                "@value": "A sequence of Unicode characters"
              }
            ],
            "https://lschema.org/targetType": [
              {
                "@value": "string"
              }
            ],
            "https://lschema.org/validation#pattern": [
              {
                "@value": "^[ \\r\\n\\t\\S]+$"
              }
            ]
          },
          {
            "@id": "http://hl7.org/fhir/ExplanationOfBenefit_Total#extension",
            "@type": [
              "https://lschema.org/Array"
            ],
            "https://lschema.org/Array#items": [
              {
                "@id": "http://hl7.org/fhir/ExplanationOfBenefit_Total#extension.*",
                "@type": [
                  "https://lschema.org/Reference"
                ],
                "https://lschema.org/Reference#reference": [
                  {
                    "@id": "http://hl7.org/fhir/Extension"
                  }
                ]
              }
            ],
            "https://lschema.org/attributeName": [
              {
                "@value": "extension"
              }
            ]
          },
          {
            "@id": "http://hl7.org/fhir/ExplanationOfBenefit_Total#modifierExtension",
            "@type": [
              "https://lschema.org/Array"
            ],
            "https://lschema.org/Array#items": [
              {
                "@id": "http://hl7.org/fhir/ExplanationOfBenefit_Total#modifierExtension.*",
                "@type": [
                  "https://lschema.org/Reference"
                ],
                "https://lschema.org/Reference#reference": [
                  {
                    "@id": "http://hl7.org/fhir/Extension"
                  }
                ]
              }
            ],
            "https://lschema.org/attributeName": [
              {
                "@value": "modifierExtension"
              }
            ]
          }
        ]
      }
    ],
    "https://lschema.org/targetType": [
      {
        "@value": "http://hl7.org/fhir/ExplanationOfBenefit_Total"
      }
    ]
  }
]