[
  {
    "@id": "http://hl7.org/fhir/Goal_Target/description",
    "@type": [
      "https://lschema.org/Overlay"
    ],
    "https://lschema.org/layer": [
      {
        "@id": "http://hl7.org/fhir/Goal_Target",
        "@type": [
          "https://lschema.org/Object",
          "http://hl7.org/fhir/Goal_Target"
        ],
        "https://lschema.org/Object/attributes": [
          {
            "@id": "http://hl7.org/fhir/Goal_Target#detailString",
            "@type": [
              "https://lschema.org/Value"
            ],
            "https://lschema.org/description": [
              {
                "@value": "The target value of the focus to be achieved to signify the fulfillment of the goal, e.g. 150 pounds, 7.0%. Either the high or low or both values of the range can be specified. When a low value is missing, it indicates that the goal is achieved at any focus value at or below the high value. Similarly, if the high value is missing, it indicates that the goal is achieved at any focus value at or above the low value."
              }
            ]
          },
          {
            "@id": "http://hl7.org/fhir/Goal_Target#id",
            "@type": [
              "https://lschema.org/Value"
            ],
            "https://lschema.org/description": [
              {
                "@value": "A sequence of Unicode characters"
              }
            ]
          },
          {
            "@id": "http://hl7.org/fhir/Goal_Target#dueDate",
            "@type": [
              "https://lschema.org/Value"
            ],
            "https://lschema.org/description": [
              {
                "@value": "Indicates either the date or the duration after start by which the goal should be met."
              }
            ]
          },
          {
            "@id": "http://hl7.org/fhir/Goal_Target#detailBoolean",
            "@type": [
              "https://lschema.org/Value"
            ],
            "https://lschema.org/description": [
              {
                "@value": "The target value of the focus to be achieved to signify the fulfillment of the goal, e.g. 150 pounds, 7.0%. Either the high or low or both values of the range can be specified. When a low value is missing, it indicates that the goal is achieved at any focus value at or below the high value. Similarly, if the high value is missing, it indicates that the goal is achieved at any focus value at or above the low value."
              }
            ]
          },
          {
            "@id": "http://hl7.org/fhir/Goal_Target#detailInteger",
            "@type": [
              "https://lschema.org/Value"
            ],
            "https://lschema.org/description": [
              {
                "@value": "The target value of the focus to be achieved to signify the fulfillment of the goal, e.g. 150 pounds, 7.0%. Either the high or low or both values of the range can be specified. When a low value is missing, it indicates that the goal is achieved at any focus value at or below the high value. Similarly, if the high value is missing, it indicates that the goal is achieved at any focus value at or above the low value."
              }
            ]
          }
        ]
      }
    ],
    "https://lschema.org/targetType": [
      {
        "@id": "http://hl7.org/fhir/Goal_Target"
      }
    ]
  }
]