[
  {
    "@id": "http://hl7.org/fhir/Patient_Communication/description",
    "@type": [
      "https://lschema.org/Overlay"
    ],
    "https://lschema.org/layer": [
      {
        "@id": "http://hl7.org/fhir/Patient_Communication",
        "@type": [
          "https://lschema.org/Object",
          "http://hl7.org/fhir/Patient_Communication"
        ],
        "https://lschema.org/Object/attributes": [
          {
            "@id": "http://hl7.org/fhir/Patient_Communication#preferred",
            "@type": [
              "https://lschema.org/Value"
            ],
            "https://lschema.org/description": [
              {
                "@value": "Value of \"true\" or \"false\""
              }
            ]
          },
          {
            "@id": "http://hl7.org/fhir/Patient_Communication#id",
            "@type": [
              "https://lschema.org/Value"
            ],
            "https://lschema.org/description": [
              {
                "@value": "A sequence of Unicode characters"
              }
            ]
          }
        ]
      }
    ],
    "https://lschema.org/targetType": [
      {
        "@id": "http://hl7.org/fhir/Patient_Communication"
      }
    ]
  }
]