[
  {
    "@id": "http://hl7.org/fhir/Procedure/description",
    "@type": [
      "https://lschema.org/Overlay"
    ],
    "https://lschema.org/layer": [
      {
        "@id": "http://hl7.org/fhir/Procedure",
        "@type": [
          "https://lschema.org/Object",
          "http://hl7.org/fhir/Procedure"
        ],
        "https://lschema.org/Object/attributes": [
          {
            "@id": "http://hl7.org/fhir/Procedure#instantiatesUri",
            "@type": [
              "https://lschema.org/Array"
            ],
            "https://lschema.org/Array/elements": [
              {
                "@id": "http://hl7.org/fhir/Procedure#instantiatesUri.*",
                "@type": [
                  "https://lschema.org/Value"
                ],
                "https://lschema.org/description": [
                  {
                    "@value": "String of characters used to identify a name or a resource"
                  }
                ]
              }
            ]
          },
          {
            "@id": "http://hl7.org/fhir/Procedure#language",
            "@type": [
              "https://lschema.org/Value"
            ],
            "https://lschema.org/description": [
              {
                "@value": "A string which has at least one character and no leading or trailing whitespace and where there is no whitespace other than single spaces in the contents"
              }
            ]
          },
          {
            "@id": "http://hl7.org/fhir/Procedure#resourceType",
            "@type": [
              "https://lschema.org/Value"
            ],
            "https://lschema.org/description": [
              {
                "@value": "This is a Procedure resource"
              }
            ]
          },
          {
            "@id": "http://hl7.org/fhir/Procedure#performedString",
            "@type": [
              "https://lschema.org/Value"
            ],
            "https://lschema.org/description": [
              {
                "@value": "Estimated or actual date, date-time, period, or age when the procedure was performed.  Allows a period to support complex procedures that span more than one date, and also allows for the length of the procedure to be captured."
              }
            ]
          },
          {
            "@id": "http://hl7.org/fhir/Procedure#implicitRules",
            "@type": [
              "https://lschema.org/Value"
            ],
            "https://lschema.org/description": [
              {
                "@value": "String of characters used to identify a name or a resource"
              }
            ]
          },
          {
            "@id": "http://hl7.org/fhir/Procedure#status",
            "@type": [
              "https://lschema.org/Value"
            ],
            "https://lschema.org/description": [
              {
                "@value": "A string which has at least one character and no leading or trailing whitespace and where there is no whitespace other than single spaces in the contents"
              }
            ]
          },
          {
            "@id": "http://hl7.org/fhir/Procedure#instantiatesCanonical",
            "@type": [
              "https://lschema.org/Array"
            ],
            "https://lschema.org/Array/elements": [
              {
                "@id": "http://hl7.org/fhir/Procedure#instantiatesCanonical.*",
                "@type": [
                  "https://lschema.org/Value"
                ],
                "https://lschema.org/description": [
                  {
                    "@value": "A URI that is a reference to a canonical URL on a FHIR resource"
                  }
                ]
              }
            ]
          },
          {
            "@id": "http://hl7.org/fhir/Procedure#performedDateTime",
            "@type": [
              "https://lschema.org/Value"
            ],
            "https://lschema.org/description": [
              {
                "@value": "Estimated or actual date, date-time, period, or age when the procedure was performed.  Allows a period to support complex procedures that span more than one date, and also allows for the length of the procedure to be captured."
              }
            ]
          }
        ]
      }
    ],
    "https://lschema.org/targetType": [
      {
        "@id": "http://hl7.org/fhir/Procedure"
      }
    ]
  }
]