[
  {
    "@id": "http://hl7.org/fhir/TerminologyCapabilities_Version/description",
    "@type": [
      "https://lschema.org/Overlay"
    ],
    "https://lschema.org/layer": [
      {
        "@id": "http://hl7.org/fhir/TerminologyCapabilities_Version",
        "@type": [
          "https://lschema.org/Object",
          "http://hl7.org/fhir/TerminologyCapabilities_Version"
        ],
        "https://lschema.org/Object/attributes": [
          {
            "@id": "http://hl7.org/fhir/TerminologyCapabilities_Version#property",
            "@type": [
              "https://lschema.org/Array"
            ],
            "https://lschema.org/Array/elements": [
              {
                "@id": "http://hl7.org/fhir/TerminologyCapabilities_Version#property.*",
                "@type": [
                  "https://lschema.org/Value"
                ],
                "https://lschema.org/description": [
                  {
                    "@value": "A string which has at least one character and no leading or trailing whitespace and where there is no whitespace other than single spaces in the contents"
                  }
                ]
              }
            ]
          },
          {
            "@id": "http://hl7.org/fhir/TerminologyCapabilities_Version#language",
            "@type": [
              "https://lschema.org/Array"
            ],
            "https://lschema.org/Array/elements": [
              {
                "@id": "http://hl7.org/fhir/TerminologyCapabilities_Version#language.*",
                "@type": [
                  "https://lschema.org/Value"
                ],
                "https://lschema.org/description": [
                  {
                    "@value": "A string which has at least one character and no leading or trailing whitespace and where there is no whitespace other than single spaces in the contents"
                  }
                ]
              }
            ]
          },
          {
            "@id": "http://hl7.org/fhir/TerminologyCapabilities_Version#code",
            "@type": [
              "https://lschema.org/Value"
            ],
            "https://lschema.org/description": [
              {
                "@value": "A sequence of Unicode characters"
              }
            ]
          },
          {
            "@id": "http://hl7.org/fhir/TerminologyCapabilities_Version#compositional",
            "@type": [
              "https://lschema.org/Value"
            ],
            "https://lschema.org/description": [
              {
                "@value": "Value of \"true\" or \"false\""
              }
            ]
          },
          {
            "@id": "http://hl7.org/fhir/TerminologyCapabilities_Version#id",
            "@type": [
              "https://lschema.org/Value"
            ],
            "https://lschema.org/description": [
              {
                "@value": "A sequence of Unicode characters"
              }
            ]
          },
          {
            "@id": "http://hl7.org/fhir/TerminologyCapabilities_Version#isDefault",
            "@type": [
              "https://lschema.org/Value"
            ],
            "https://lschema.org/description": [
              {
                "@value": "Value of \"true\" or \"false\""
              }
            ]
          }
        ]
      }
    ],
    "https://lschema.org/targetType": [
      {
        "@id": "http://hl7.org/fhir/TerminologyCapabilities_Version"
      }
    ]
  }
]